aurcore/__init__.py
aurcore/aur.py
aurcore/event/__init__.py
aurcore/log/__init__.py
aurcore/persist/__init__.py
aurcore/py.typed
aurcore/util/__init__.py
aurcore/util/flattener.py
aurcore/util/tb.py
aurcore-1.2.16.dist-info/WHEEL
aurcore-1.2.16.dist-info/METADATA
aurcore-1.2.16.dist-info/RECORD
